ascall.py
ascall-0.1.1.dist-info/LICENSE
ascall-0.1.1.dist-info/WHEEL
ascall-0.1.1.dist-info/METADATA
ascall-0.1.1.dist-info/RECORD
