Metadata-Version: 2.1
Name: ascall
Version: 0.1.1
Summary: ascall用于自动识别同步或异步的可调用对象，然后进行转换并执行异步调用返回结果。
Keywords: async,asyncio,func,function
Author-email: vastxiao <vastxiao@gmail.com>
Requires-Python: >=3.9
Classifier: License :: OSI Approved :: MIT License
Project-URL: Home, https://vastxiao.github.io/
